lib_shopware6_api_base/.gitignore
lib_shopware6_api_base/__init__.py
lib_shopware6_api_base/__init__conf__.py
lib_shopware6_api_base/conf_shopware6_api_base_classes.py
lib_shopware6_api_base/conf_shopware6_api_base_docker_testcontainer.py
lib_shopware6_api_base/lib_shopware6_api_base.py
lib_shopware6_api_base/lib_shopware6_api_base_cli.py
lib_shopware6_api_base/lib_shopware6_api_base_criteria.py
lib_shopware6_api_base/lib_shopware6_api_base_criteria_aggregation.py
lib_shopware6_api_base/lib_shopware6_api_base_criteria_filter.py
lib_shopware6_api_base/lib_shopware6_api_base_criteria_sorting.py
lib_shopware6_api_base/lib_shopware6_api_base_helpers.py
lib_shopware6_api_base/py.typed
lib_shopware6_api_base-2.1.9.dist-info/LICENSE
lib_shopware6_api_base-2.1.9.dist-info/METADATA
lib_shopware6_api_base-2.1.9.dist-info/WHEEL
lib_shopware6_api_base-2.1.9.dist-info/entry_points.txt
lib_shopware6_api_base-2.1.9.dist-info/top_level.txt
lib_shopware6_api_base-2.1.9.dist-info/RECORD
